autoviz/AutoViz_Class.py
autoviz/AutoViz_Holo.py
autoviz/AutoViz_NLP.py
autoviz/AutoViz_Utils.py
autoviz/__init__.py
autoviz/__version__.py
autoviz/classify_method.py
autoviz/tests/__init__.py
autoviz/tests/test_autoviz_class.py
autoviz/tests/test_deps.py
autoviz-0.1.905.dist-info/LICENSE
autoviz-0.1.905.dist-info/METADATA
autoviz-0.1.905.dist-info/WHEEL
autoviz-0.1.905.dist-info/top_level.txt
autoviz-0.1.905.dist-info/RECORD
