Metadata-Version: 2.1
Name: autoviz
Version: 0.1.905
Summary: Automatically Visualize any dataset, any size with a single line of code
Home-page: https://github.com/AutoViML/AutoViz.git
Author: Ram Seshadri
License: Apache License 2.0
Classifier: Programming Language :: Python :: 3
Classifier: Operating System :: OS Independent
License-File: LICENSE
Requires-Dist: xlrd
Requires-Dist: wordcloud
Requires-Dist: emoji
Requires-Dist: pyamg
Requires-Dist: scikit-learn
Requires-Dist: statsmodels
Requires-Dist: nltk
Requires-Dist: textblob
Requires-Dist: xgboost (<1.7,>=0.82)
Requires-Dist: fsspec (>=0.8.3)
Requires-Dist: typing-extensions (>=4.1.1)
Requires-Dist: pandas-dq (>=1.29)
Requires-Dist: numpy (>=1.24.0)
Requires-Dist: hvplot (>=0.9.2)
Requires-Dist: holoviews (>=1.16.0)
Requires-Dist: panel (>=1.4.0)
Requires-Dist: pandas (>=2.0)
Requires-Dist: matplotlib (>3.7.4)
Requires-Dist: seaborn (>0.12.2)
